saber_primo/__init__.py
saber_primo-1.0.dist-info/LICENSE.txt
saber_primo-1.0.dist-info/METADATA
saber_primo-1.0.dist-info/WHEEL
saber_primo-1.0.dist-info/top_level.txt
saber_primo-1.0.dist-info/RECORD
